{
	"collections_info":[
		{
			"name": "Технарям",
			"description": "Валентин Каверин писал о пьесе: «Бег» разрушает условные границы жанра, то перед нами психологическая драма, то фантасмагория, почти выпадающая из реальных представлений об окружающем мире».",
			"img_url": "http://kurtr.ru/photos/geeks.jpg",
			"events_list": [502642, 502352, 503751, 499880, 502751]
		},

		{
			"name": "Детям 13-15 лет",
			"description": "Чтобы дети полюбили театр, чтобы детям было интересно. Спектакли о дружбе, любви и преданности. Православный стендап, Классический театр, Мюзикл и Классическая комедия.",
			"img_url": "http://kurtr.ru/photos/teens.jpg",
			"events_list": [502293, 501551, 503806, 502975]
		},

		{
			"name": "Гуманитариям",
			"description": "Шекспир, Пушкин, Ерофеев, Островский. Классические произведения. Режиссеры — лауреаты Золотой маски и Хрустальной Турандот.",
			"img_url": "http://kurtr.ru/photos/humanist.jpg",
			"events_list": [498414, 498198, 501543, 503568, 502488]
		},

		{
			"name": "Детям 6-8 лет",
			"description": "Спектакли для родителей и детей. О правде, о победе над страхами и о мечтах.",
			"img_url": "http://kurtr.ru/photos/children.jpg",
			"events_list": [503724, 502671, 502252, 499907, 503806]
		},

		{
			"name": "Мюзиклы",
			"description": "Первый мюзикл в России. Первый мюзикл в России, в котором был использован паркур.",
			"img_url": "http://kurtr.ru/photos/musical2.jpg",
			"events_list": [500545, 502953, 503126, 502940, 503186]
		},

		{
			"name": "Новичкам",
			"description": "Тем, кто ищет свое — от классической комедии Бомарше до пластической постановки Достоевского.",
			"img_url": "http://kurtr.ru/photos/do_not_like_the_theater.jpg",
			"events_list": [502277, 501563, 503779, 502343, 501805]
		},

		{
			"name": "Вечер с девушкой",
			"description": "Истории любви. Спектакль, который 27 лет на сцене и премьера, получившая 7 номинаций на премию Золотая Маска.",
			"img_url": "http://kurtr.ru/photos/together_evening.jpg",
			"events_list": [503186, 501575,502940,503800,500994]
		},

		{
			"name": "Современные истории о жизни",
			"description": "Театр как разговор о жизни. Театр как рассказ о судьбах.",
			"img_url": "http://kurtr.ru/photos/together_life.jpg",
			"events_list": [502967, 501320, 503800, 503792, 501746, 502739]
		},

		{
			"name": "Русская классика",
			"description": "Классика бессмертна. В любом настроении, в любом возрасте, для очищения души от повседневной суеты.",
			"img_url": "http://kurtr.ru/photos/together_theatre.jpg",
			"events_list": [502972, 498381, 502015, 502673, 501808]
		}
	]
}